{
  "video_info": {
    "filename": "bb111.MP4",
    "fps": 59,
    "width": 1920,
    "height": 1080,
    "total_frames": 166
  },
  "frames": [
    {
      "frame_number": 1,
      "timestamp": 0.017,
      "joints": {
        "shoulder_angle": 149.95,
        "elbow_angle": 171.68,
        "hip_angle": 164.8,
        "knee_angle": 162.92,
        "ankle_angle": 164.07
      }
    },
    {
      "frame_number": 2,
      "timestamp": 0.034,
      "joints": {
        "shoulder_angle": 149.17,
        "elbow_angle": 173.45,
        "hip_angle": 165.6,
        "knee_angle": 162.8,
        "ankle_angle": 166.97
      }
    },
    {
      "frame_number": 3,
      "timestamp": 0.051,
      "joints": {
        "shoulder_angle": 149.32,
        "elbow_angle": 173.61,
        "hip_angle": 165.32,
        "knee_angle": 161.65,
        "ankle_angle": 168.01
      }
    },
    {
      "frame_number": 4,
      "timestamp": 0.068,
      "joints": {
        "shoulder_angle": 149.72,
        "elbow_angle": 173.39,
        "hip_angle": 164.98,
        "knee_angle": 159.89,
        "ankle_angle": 168.15
      }
    },
    {
      "frame_number": 5,
      "timestamp": 0.085,
      "joints": {
        "shoulder_angle": 149.99,
        "elbow_angle": 170.83,
        "hip_angle": 164.75,
        "knee_angle": 158.01,
        "ankle_angle": 168.72
      }
    },
    {
      "frame_number": 6,
      "timestamp": 0.102,
      "joints": {
        "shoulder_angle": 152.52,
        "elbow_angle": 168.7,
        "hip_angle": 164.14,
        "knee_angle": 155.97,
        "ankle_angle": 168.16
      }
    },
    {
      "frame_number": 7,
      "timestamp": 0.119,
      "joints": {
        "shoulder_angle": 153.79,
        "elbow_angle": 166.51,
        "hip_angle": 162.09,
        "knee_angle": 153.17,
        "ankle_angle": 165.84
      }
    },
    {
      "frame_number": 8,
      "timestamp": 0.136,
      "joints": {
        "shoulder_angle": 155.63,
        "elbow_angle": 166.31,
        "hip_angle": 160.65,
        "knee_angle": 151.0,
        "ankle_angle": 161.77
      }
    },
    {
      "frame_number": 9,
      "timestamp": 0.153,
      "joints": {
        "shoulder_angle": 159.6,
        "elbow_angle": 166.89,
        "hip_angle": 159.51,
        "knee_angle": 148.66,
        "ankle_angle": 157.43
      }
    },
    {
      "frame_number": 10,
      "timestamp": 0.169,
      "joints": {
        "shoulder_angle": 162.94,
        "elbow_angle": 168.8,
        "hip_angle": 158.78,
        "knee_angle": 146.88,
        "ankle_angle": 156.73
      }
    },
    {
      "frame_number": 11,
      "timestamp": 0.186,
      "joints": {
        "shoulder_angle": 166.46,
        "elbow_angle": 170.95,
        "hip_angle": 157.71,
        "knee_angle": 144.68,
        "ankle_angle": 153.15
      }
    },
    {
      "frame_number": 12,
      "timestamp": 0.203,
      "joints": {
        "shoulder_angle": 169.56,
        "elbow_angle": 173.12,
        "hip_angle": 156.09,
        "knee_angle": 142.03,
        "ankle_angle": 154.88
      }
    },
    {
      "frame_number": 13,
      "timestamp": 0.22,
      "joints": {
        "shoulder_angle": 172.94,
        "elbow_angle": 175.7,
        "hip_angle": 155.09,
        "knee_angle": 140.02,
        "ankle_angle": 153.06
      }
    },
    {
      "frame_number": 14,
      "timestamp": 0.237,
      "joints": {
        "shoulder_angle": 176.69,
        "elbow_angle": 175.59,
        "hip_angle": 154.25,
        "knee_angle": 138.56,
        "ankle_angle": 151.82
      }
    },
    {
      "frame_number": 15,
      "timestamp": 0.254,
      "joints": {
        "shoulder_angle": 178.0,
        "elbow_angle": 175.57,
        "hip_angle": 153.04,
        "knee_angle": 137.69,
        "ankle_angle": 152.86
      }
    },
    {
      "frame_number": 16,
      "timestamp": 0.271,
      "joints": {
        "shoulder_angle": 176.48,
        "elbow_angle": 176.43,
        "hip_angle": 153.04,
        "knee_angle": 137.01,
        "ankle_angle": 154.38
      }
    },
    {
      "frame_number": 17,
      "timestamp": 0.288,
      "joints": {
        "shoulder_angle": 172.63,
        "elbow_angle": 174.72,
        "hip_angle": 154.44,
        "knee_angle": 136.96,
        "ankle_angle": 155.02
      }
    },
    {
      "frame_number": 18,
      "timestamp": 0.305,
      "joints": {
        "shoulder_angle": 174.37,
        "elbow_angle": 174.95,
        "hip_angle": 155.67,
        "knee_angle": 137.62,
        "ankle_angle": 153.16
      }
    },
    {
      "frame_number": 19,
      "timestamp": 0.322,
      "joints": {
        "shoulder_angle": 172.47,
        "elbow_angle": 171.25,
        "hip_angle": 157.24,
        "knee_angle": 137.57,
        "ankle_angle": 156.63
      }
    },
    {
      "frame_number": 20,
      "timestamp": 0.339,
      "joints": {
        "shoulder_angle": 168.36,
        "elbow_angle": 172.54,
        "hip_angle": 159.14,
        "knee_angle": 139.24,
        "ankle_angle": 155.71
      }
    },
    {
      "frame_number": 21,
      "timestamp": 0.356,
      "joints": {
        "shoulder_angle": 164.85,
        "elbow_angle": 170.41,
        "hip_angle": 156.54,
        "knee_angle": 137.54,
        "ankle_angle": 157.85
      }
    },
    {
      "frame_number": 22,
      "timestamp": 0.373,
      "joints": {
        "shoulder_angle": 162.28,
        "elbow_angle": 172.08,
        "hip_angle": 153.48,
        "knee_angle": 137.05,
        "ankle_angle": 154.49
      }
    },
    {
      "frame_number": 23,
      "timestamp": 0.39,
      "joints": {
        "shoulder_angle": 160.45,
        "elbow_angle": 171.94,
        "hip_angle": 152.6,
        "knee_angle": 135.86,
        "ankle_angle": 157.38
      }
    },
    {
      "frame_number": 24,
      "timestamp": 0.407,
      "joints": {
        "shoulder_angle": 158.72,
        "elbow_angle": 171.01,
        "hip_angle": 151.37,
        "knee_angle": 134.17,
        "ankle_angle": 159.31
      }
    },
    {
      "frame_number": 25,
      "timestamp": 0.424,
      "joints": {
        "shoulder_angle": 158.81,
        "elbow_angle": 166.95,
        "hip_angle": 152.05,
        "knee_angle": 134.97,
        "ankle_angle": 159.9
      }
    },
    {
      "frame_number": 26,
      "timestamp": 0.441,
      "joints": {
        "shoulder_angle": 157.26,
        "elbow_angle": 165.53,
        "hip_angle": 152.03,
        "knee_angle": 135.05,
        "ankle_angle": 163.37
      }
    },
    {
      "frame_number": 27,
      "timestamp": 0.458,
      "joints": {
        "shoulder_angle": 156.44,
        "elbow_angle": 161.87,
        "hip_angle": 152.47,
        "knee_angle": 135.89,
        "ankle_angle": 162.67
      }
    },
    {
      "frame_number": 28,
      "timestamp": 0.475,
      "joints": {
        "shoulder_angle": 153.82,
        "elbow_angle": 159.96,
        "hip_angle": 153.84,
        "knee_angle": 137.4,
        "ankle_angle": 163.71
      }
    },
    {
      "frame_number": 29,
      "timestamp": 0.492,
      "joints": {
        "shoulder_angle": 153.15,
        "elbow_angle": 157.6,
        "hip_angle": 155.61,
        "knee_angle": 139.85,
        "ankle_angle": 162.12
      }
    },
    {
      "frame_number": 30,
      "timestamp": 0.508,
      "joints": {
        "shoulder_angle": 152.05,
        "elbow_angle": 156.12,
        "hip_angle": 157.15,
        "knee_angle": 141.72,
        "ankle_angle": 161.03
      }
    },
    {
      "frame_number": 31,
      "timestamp": 0.525,
      "joints": {
        "shoulder_angle": 150.21,
        "elbow_angle": 152.88,
        "hip_angle": 159.06,
        "knee_angle": 143.68,
        "ankle_angle": 158.98
      }
    },
    {
      "frame_number": 32,
      "timestamp": 0.542,
      "joints": {
        "shoulder_angle": 149.38,
        "elbow_angle": 149.62,
        "hip_angle": 159.74,
        "knee_angle": 146.09,
        "ankle_angle": 154.03
      }
    },
    {
      "frame_number": 33,
      "timestamp": 0.559,
      "joints": {
        "shoulder_angle": 148.91,
        "elbow_angle": 145.68,
        "hip_angle": 161.41,
        "knee_angle": 150.44,
        "ankle_angle": 151.61
      }
    },
    {
      "frame_number": 34,
      "timestamp": 0.576,
      "joints": {
        "shoulder_angle": 148.15,
        "elbow_angle": 141.78,
        "hip_angle": 162.96,
        "knee_angle": 153.63,
        "ankle_angle": 149.61
      }
    },
    {
      "frame_number": 35,
      "timestamp": 0.593,
      "joints": {
        "shoulder_angle": 147.11,
        "elbow_angle": 138.75,
        "hip_angle": 163.74,
        "knee_angle": 155.47,
        "ankle_angle": 151.44
      }
    },
    {
      "frame_number": 36,
      "timestamp": 0.61,
      "joints": {
        "shoulder_angle": 145.93,
        "elbow_angle": 134.41,
        "hip_angle": 164.73,
        "knee_angle": 157.85,
        "ankle_angle": 154.57
      }
    },
    {
      "frame_number": 37,
      "timestamp": 0.627,
      "joints": {
        "shoulder_angle": 146.74,
        "elbow_angle": 128.69,
        "hip_angle": 165.25,
        "knee_angle": 159.44,
        "ankle_angle": 158.13
      }
    },
    {
      "frame_number": 38,
      "timestamp": 0.644,
      "joints": {
        "shoulder_angle": 146.86,
        "elbow_angle": 122.64,
        "hip_angle": 165.47,
        "knee_angle": 161.2,
        "ankle_angle": 159.73
      }
    },
    {
      "frame_number": 39,
      "timestamp": 0.661,
      "joints": {
        "shoulder_angle": 146.8,
        "elbow_angle": 119.31,
        "hip_angle": 166.2,
        "knee_angle": 163.59,
        "ankle_angle": 160.55
      }
    },
    {
      "frame_number": 40,
      "timestamp": 0.678,
      "joints": {
        "shoulder_angle": 146.94,
        "elbow_angle": 112.62,
        "hip_angle": 166.92,
        "knee_angle": 165.7,
        "ankle_angle": 161.83
      }
    },
    {
      "frame_number": 41,
      "timestamp": 0.695,
      "joints": {
        "shoulder_angle": 147.37,
        "elbow_angle": 109.41,
        "hip_angle": 167.62,
        "knee_angle": 167.36,
        "ankle_angle": 162.78
      }
    },
    {
      "frame_number": 42,
      "timestamp": 0.712,
      "joints": {
        "shoulder_angle": 147.82,
        "elbow_angle": 106.66,
        "hip_angle": 168.54,
        "knee_angle": 169.91,
        "ankle_angle": 164.1
      }
    },
    {
      "frame_number": 43,
      "timestamp": 0.729,
      "joints": {
        "shoulder_angle": 147.63,
        "elbow_angle": 104.14,
        "hip_angle": 169.22,
        "knee_angle": 172.38,
        "ankle_angle": 164.67
      }
    },
    {
      "frame_number": 44,
      "timestamp": 0.746,
      "joints": {
        "shoulder_angle": 148.29,
        "elbow_angle": 103.3,
        "hip_angle": 169.51,
        "knee_angle": 174.54,
        "ankle_angle": 163.56
      }
    },
    {
      "frame_number": 45,
      "timestamp": 0.763,
      "joints": {
        "shoulder_angle": 148.29,
        "elbow_angle": 100.72,
        "hip_angle": 169.17,
        "knee_angle": 176.08,
        "ankle_angle": 161.84
      }
    },
    {
      "frame_number": 46,
      "timestamp": 0.78,
      "joints": {
        "shoulder_angle": 148.51,
        "elbow_angle": 102.02,
        "hip_angle": 169.0,
        "knee_angle": 176.88,
        "ankle_angle": 160.41
      }
    },
    {
      "frame_number": 47,
      "timestamp": 0.797,
      "joints": {
        "shoulder_angle": 150.1,
        "elbow_angle": 100.68,
        "hip_angle": 168.51,
        "knee_angle": 177.27,
        "ankle_angle": 162.85
      }
    },
    {
      "frame_number": 48,
      "timestamp": 0.814,
      "joints": {
        "shoulder_angle": 151.87,
        "elbow_angle": 101.66,
        "hip_angle": 168.06,
        "knee_angle": 177.55,
        "ankle_angle": 162.65
      }
    },
    {
      "frame_number": 49,
      "timestamp": 0.831,
      "joints": {
        "shoulder_angle": 152.47,
        "elbow_angle": 109.74,
        "hip_angle": 167.26,
        "knee_angle": 177.68,
        "ankle_angle": 162.3
      }
    },
    {
      "frame_number": 50,
      "timestamp": 0.847,
      "joints": {
        "shoulder_angle": 154.4,
        "elbow_angle": 115.98,
        "hip_angle": 166.53,
        "knee_angle": 177.06,
        "ankle_angle": 162.22
      }
    },
    {
      "frame_number": 51,
      "timestamp": 0.864,
      "joints": {
        "shoulder_angle": 153.97,
        "elbow_angle": 126.32,
        "hip_angle": 166.44,
        "knee_angle": 176.39,
        "ankle_angle": 162.63
      }
    },
    {
      "frame_number": 52,
      "timestamp": 0.881,
      "joints": {
        "shoulder_angle": 153.8,
        "elbow_angle": 136.45,
        "hip_angle": 166.22,
        "knee_angle": 176.23,
        "ankle_angle": 162.81
      }
    },
    {
      "frame_number": 53,
      "timestamp": 0.898,
      "joints": {
        "shoulder_angle": 155.37,
        "elbow_angle": 142.36,
        "hip_angle": 165.93,
        "knee_angle": 175.98,
        "ankle_angle": 161.31
      }
    },
    {
      "frame_number": 54,
      "timestamp": 0.915,
      "joints": {
        "shoulder_angle": 156.53,
        "elbow_angle": 147.69,
        "hip_angle": 165.45,
        "knee_angle": 175.8,
        "ankle_angle": 159.64
      }
    },
    {
      "frame_number": 55,
      "timestamp": 0.932,
      "joints": {
        "shoulder_angle": 157.24,
        "elbow_angle": 154.54,
        "hip_angle": 164.78,
        "knee_angle": 176.95,
        "ankle_angle": 152.55
      }
    },
    {
      "frame_number": 56,
      "timestamp": 0.949,
      "joints": {
        "shoulder_angle": 158.74,
        "elbow_angle": 159.97,
        "hip_angle": 164.27,
        "knee_angle": 176.45,
        "ankle_angle": 152.24
      }
    },
    {
      "frame_number": 57,
      "timestamp": 0.966,
      "joints": {
        "shoulder_angle": 160.51,
        "elbow_angle": 162.17,
        "hip_angle": 163.76,
        "knee_angle": 176.47,
        "ankle_angle": 150.98
      }
    },
    {
      "frame_number": 58,
      "timestamp": 0.983,
      "joints": {
        "shoulder_angle": 164.41,
        "elbow_angle": 165.89,
        "hip_angle": 163.81,
        "knee_angle": 176.44,
        "ankle_angle": 151.27
      }
    },
    {
      "frame_number": 59,
      "timestamp": 1.0,
      "joints": {
        "shoulder_angle": 166.83,
        "elbow_angle": 166.95,
        "hip_angle": 164.71,
        "knee_angle": 177.38,
        "ankle_angle": 156.11
      }
    },
    {
      "frame_number": 60,
      "timestamp": 1.017,
      "joints": {
        "shoulder_angle": 170.36,
        "elbow_angle": 168.14,
        "hip_angle": 165.1,
        "knee_angle": 177.4,
        "ankle_angle": 157.9
      }
    },
    {
      "frame_number": 61,
      "timestamp": 1.034,
      "joints": {
        "shoulder_angle": 173.23,
        "elbow_angle": 166.37,
        "hip_angle": 166.64,
        "knee_angle": 177.76,
        "ankle_angle": 159.03
      }
    },
    {
      "frame_number": 62,
      "timestamp": 1.051,
      "joints": {
        "shoulder_angle": 174.79,
        "elbow_angle": 174.44,
        "hip_angle": 166.92,
        "knee_angle": 177.91,
        "ankle_angle": 160.61
      }
    },
    {
      "frame_number": 63,
      "timestamp": 1.068,
      "joints": {
        "shoulder_angle": 174.74,
        "elbow_angle": 176.13,
        "hip_angle": 167.12,
        "knee_angle": 177.73,
        "ankle_angle": 160.78
      }
    },
    {
      "frame_number": 64,
      "timestamp": 1.085,
      "joints": {
        "shoulder_angle": 175.94,
        "elbow_angle": 175.15,
        "hip_angle": 166.41,
        "knee_angle": 178.13,
        "ankle_angle": 162.91
      }
    },
    {
      "frame_number": 65,
      "timestamp": 1.102,
      "joints": {
        "shoulder_angle": 178.28,
        "elbow_angle": 175.44,
        "hip_angle": 166.79,
        "knee_angle": 178.16,
        "ankle_angle": 162.58
      }
    },
    {
      "frame_number": 66,
      "timestamp": 1.119,
      "joints": {
        "shoulder_angle": 165.53,
        "elbow_angle": 173.37,
        "hip_angle": 166.61,
        "knee_angle": 178.59,
        "ankle_angle": 156.93
      }
    },
    {
      "frame_number": 67,
      "timestamp": 1.136,
      "joints": {
        "shoulder_angle": 161.84,
        "elbow_angle": 170.51,
        "hip_angle": 166.14,
        "knee_angle": 179.16,
        "ankle_angle": 155.08
      }
    },
    {
      "frame_number": 68,
      "timestamp": 1.153,
      "joints": {
        "shoulder_angle": 155.03,
        "elbow_angle": 171.88,
        "hip_angle": 165.35,
        "knee_angle": 177.96,
        "ankle_angle": 157.75
      }
    },
    {
      "frame_number": 69,
      "timestamp": 1.169,
      "joints": {
        "shoulder_angle": 152.27,
        "elbow_angle": 167.93,
        "hip_angle": 164.28,
        "knee_angle": 176.54,
        "ankle_angle": 160.07
      }
    },
    {
      "frame_number": 70,
      "timestamp": 1.186,
      "joints": {
        "shoulder_angle": 143.31,
        "elbow_angle": 152.57,
        "hip_angle": 162.83,
        "knee_angle": 174.68,
        "ankle_angle": 161.61
      }
    },
    {
      "frame_number": 71,
      "timestamp": 1.203,
      "joints": {
        "shoulder_angle": 141.5,
        "elbow_angle": 142.31,
        "hip_angle": 160.49,
        "knee_angle": 171.65,
        "ankle_angle": 163.07
      }
    },
    {
      "frame_number": 72,
      "timestamp": 1.22,
      "joints": {
        "shoulder_angle": 134.29,
        "elbow_angle": 141.77,
        "hip_angle": 158.51,
        "knee_angle": 168.88,
        "ankle_angle": 164.34
      }
    },
    {
      "frame_number": 73,
      "timestamp": 1.237,
      "joints": {
        "shoulder_angle": 123.56,
        "elbow_angle": 164.44,
        "hip_angle": 155.73,
        "knee_angle": 165.01,
        "ankle_angle": 167.14
      }
    },
    {
      "frame_number": 74,
      "timestamp": 1.254,
      "joints": {
        "shoulder_angle": 117.13,
        "elbow_angle": 170.31,
        "hip_angle": 153.74,
        "knee_angle": 161.53,
        "ankle_angle": 167.34
      }
    },
    {
      "frame_number": 75,
      "timestamp": 1.271,
      "joints": {
        "shoulder_angle": 119.11,
        "elbow_angle": 172.41,
        "hip_angle": 151.11,
        "knee_angle": 158.16,
        "ankle_angle": 168.34
      }
    },
    {
      "frame_number": 76,
      "timestamp": 1.288,
      "joints": {
        "shoulder_angle": 120.56,
        "elbow_angle": 170.55,
        "hip_angle": 148.85,
        "knee_angle": 156.25,
        "ankle_angle": 167.06
      }
    },
    {
      "frame_number": 77,
      "timestamp": 1.305,
      "joints": {
        "shoulder_angle": 115.72,
        "elbow_angle": 157.87,
        "hip_angle": 144.95,
        "knee_angle": 155.13,
        "ankle_angle": 157.12
      }
    },
    {
      "frame_number": 78,
      "timestamp": 1.322,
      "joints": {
        "shoulder_angle": 115.0,
        "elbow_angle": 158.69,
        "hip_angle": 141.09,
        "knee_angle": 151.77,
        "ankle_angle": 157.21
      }
    },
    {
      "frame_number": 79,
      "timestamp": 1.339,
      "joints": {
        "shoulder_angle": 124.33,
        "elbow_angle": 159.89,
        "hip_angle": 139.74,
        "knee_angle": 150.58,
        "ankle_angle": 153.48
      }
    },
    {
      "frame_number": 80,
      "timestamp": 1.356,
      "joints": {
        "shoulder_angle": 126.74,
        "elbow_angle": 154.41,
        "hip_angle": 136.45,
        "knee_angle": 148.58,
        "ankle_angle": 154.67
      }
    },
    {
      "frame_number": 81,
      "timestamp": 1.373,
      "joints": {
        "shoulder_angle": 139.52,
        "elbow_angle": 144.22,
        "hip_angle": 130.28,
        "knee_angle": 146.26,
        "ankle_angle": 153.28
      }
    },
    {
      "frame_number": 82,
      "timestamp": 1.39,
      "joints": {
        "shoulder_angle": 145.93,
        "elbow_angle": 148.3,
        "hip_angle": 126.86,
        "knee_angle": 141.75,
        "ankle_angle": 152.67
      }
    },
    {
      "frame_number": 83,
      "timestamp": 1.407,
      "joints": {
        "shoulder_angle": 151.62,
        "elbow_angle": 164.89,
        "hip_angle": 119.32,
        "knee_angle": 126.27,
        "ankle_angle": 157.31
      }
    },
    {
      "frame_number": 84,
      "timestamp": 1.424,
      "joints": {
        "shoulder_angle": 167.62,
        "elbow_angle": 178.01,
        "hip_angle": 94.17,
        "knee_angle": 131.65,
        "ankle_angle": 163.92
      }
    },
    {
      "frame_number": 85,
      "timestamp": 1.441,
      "joints": {
        "shoulder_angle": 168.67,
        "elbow_angle": 173.56,
        "hip_angle": 125.69,
        "knee_angle": 131.61,
        "ankle_angle": 150.91
      }
    },
    {
      "frame_number": 86,
      "timestamp": 1.458,
      "joints": {
        "shoulder_angle": 172.23,
        "elbow_angle": 176.89,
        "hip_angle": 132.53,
        "knee_angle": 141.36,
        "ankle_angle": 136.09
      }
    },
    {
      "frame_number": 87,
      "timestamp": 1.475,
      "joints": {
        "shoulder_angle": 170.7,
        "elbow_angle": 167.75,
        "hip_angle": 133.28,
        "knee_angle": 142.56,
        "ankle_angle": 135.58
      }
    },
    {
      "frame_number": 88,
      "timestamp": 1.492,
      "joints": {
        "shoulder_angle": 172.55,
        "elbow_angle": 164.14,
        "hip_angle": 128.47,
        "knee_angle": 139.3,
        "ankle_angle": 149.13
      }
    },
    {
      "frame_number": 89,
      "timestamp": 1.508,
      "joints": {
        "shoulder_angle": 174.52,
        "elbow_angle": 165.09,
        "hip_angle": 124.29,
        "knee_angle": 119.91,
        "ankle_angle": 130.08
      }
    },
    {
      "frame_number": 90,
      "timestamp": 1.525,
      "joints": {
        "shoulder_angle": 166.15,
        "elbow_angle": 171.79,
        "hip_angle": 118.85,
        "knee_angle": 122.49,
        "ankle_angle": 138.91
      }
    },
    {
      "frame_number": 91,
      "timestamp": 1.542,
      "joints": {
        "shoulder_angle": 163.15,
        "elbow_angle": 168.14,
        "hip_angle": 118.0,
        "knee_angle": 125.01,
        "ankle_angle": 124.75
      }
    },
    {
      "frame_number": 92,
      "timestamp": 1.559,
      "joints": {
        "shoulder_angle": 157.79,
        "elbow_angle": 166.01,
        "hip_angle": 113.69,
        "knee_angle": 118.29,
        "ankle_angle": 134.41
      }
    },
    {
      "frame_number": 93,
      "timestamp": 1.576,
      "joints": {
        "shoulder_angle": 157.35,
        "elbow_angle": 161.35,
        "hip_angle": 94.0,
        "knee_angle": 105.24,
        "ankle_angle": 151.83
      }
    },
    {
      "frame_number": 94,
      "timestamp": 1.593,
      "joints": {
        "shoulder_angle": 152.11,
        "elbow_angle": 161.05,
        "hip_angle": 83.83,
        "knee_angle": 112.47,
        "ankle_angle": 136.09
      }
    },
    {
      "frame_number": 95,
      "timestamp": 1.61,
      "joints": {
        "shoulder_angle": 148.11,
        "elbow_angle": 160.23,
        "hip_angle": 78.73,
        "knee_angle": 110.04,
        "ankle_angle": 144.31
      }
    },
    {
      "frame_number": 96,
      "timestamp": 1.627,
      "joints": {
        "shoulder_angle": 140.88,
        "elbow_angle": 164.38,
        "hip_angle": 103.76,
        "knee_angle": 128.84,
        "ankle_angle": 150.2
      }
    },
    {
      "frame_number": 97,
      "timestamp": 1.644,
      "joints": {
        "shoulder_angle": 134.21,
        "elbow_angle": 163.47,
        "hip_angle": 114.61,
        "knee_angle": 130.33,
        "ankle_angle": 148.51
      }
    },
    {
      "frame_number": 98,
      "timestamp": 1.661,
      "joints": {
        "shoulder_angle": 132.29,
        "elbow_angle": 152.39,
        "hip_angle": 117.29,
        "knee_angle": 131.05,
        "ankle_angle": 151.72
      }
    },
    {
      "frame_number": 99,
      "timestamp": 1.678,
      "joints": {
        "shoulder_angle": 127.75,
        "elbow_angle": 145.67,
        "hip_angle": 120.37,
        "knee_angle": 132.05,
        "ankle_angle": 151.87
      }
    },
    {
      "frame_number": 100,
      "timestamp": 1.695,
      "joints": {
        "shoulder_angle": 128.47,
        "elbow_angle": 136.48,
        "hip_angle": 125.03,
        "knee_angle": 134.34,
        "ankle_angle": 152.64
      }
    },
    {
      "frame_number": 101,
      "timestamp": 1.712,
      "joints": {
        "shoulder_angle": 126.18,
        "elbow_angle": 131.61,
        "hip_angle": 129.1,
        "knee_angle": 135.78,
        "ankle_angle": 152.08
      }
    },
    {
      "frame_number": 102,
      "timestamp": 1.729,
      "joints": {
        "shoulder_angle": 126.56,
        "elbow_angle": 107.26,
        "hip_angle": 133.66,
        "knee_angle": 138.67,
        "ankle_angle": 151.2
      }
    },
    {
      "frame_number": 103,
      "timestamp": 1.746,
      "joints": {
        "shoulder_angle": 114.23,
        "elbow_angle": 112.97,
        "hip_angle": 136.86,
        "knee_angle": 140.68,
        "ankle_angle": 156.04
      }
    },
    {
      "frame_number": 104,
      "timestamp": 1.763,
      "joints": {
        "shoulder_angle": 107.98,
        "elbow_angle": 112.61,
        "hip_angle": 140.75,
        "knee_angle": 142.34,
        "ankle_angle": 146.35
      }
    },
    {
      "frame_number": 105,
      "timestamp": 1.78,
      "joints": {
        "shoulder_angle": 103.75,
        "elbow_angle": 108.11,
        "hip_angle": 145.53,
        "knee_angle": 145.22,
        "ankle_angle": 140.15
      }
    },
    {
      "frame_number": 106,
      "timestamp": 1.797,
      "joints": {
        "shoulder_angle": 98.56,
        "elbow_angle": 106.8,
        "hip_angle": 149.91,
        "knee_angle": 147.43,
        "ankle_angle": 132.9
      }
    },
    {
      "frame_number": 107,
      "timestamp": 1.814,
      "joints": {
        "shoulder_angle": 96.8,
        "elbow_angle": 104.83,
        "hip_angle": 156.33,
        "knee_angle": 150.89,
        "ankle_angle": 126.61
      }
    },
    {
      "frame_number": 108,
      "timestamp": 1.831,
      "joints": {
        "shoulder_angle": 97.67,
        "elbow_angle": 104.55,
        "hip_angle": 164.82,
        "knee_angle": 156.45,
        "ankle_angle": 122.71
      }
    },
    {
      "frame_number": 109,
      "timestamp": 1.847,
      "joints": {
        "shoulder_angle": 99.53,
        "elbow_angle": 103.57,
        "hip_angle": 170.57,
        "knee_angle": 160.93,
        "ankle_angle": 116.53
      }
    },
    {
      "frame_number": 110,
      "timestamp": 1.864,
      "joints": {
        "shoulder_angle": 104.97,
        "elbow_angle": 89.08,
        "hip_angle": 175.37,
        "knee_angle": 164.81,
        "ankle_angle": 126.53
      }
    },
    {
      "frame_number": 111,
      "timestamp": 1.881,
      "joints": {
        "shoulder_angle": 119.73,
        "elbow_angle": 75.67,
        "hip_angle": 177.31,
        "knee_angle": 159.87,
        "ankle_angle": 131.2
      }
    },
    {
      "frame_number": 112,
      "timestamp": 1.898,
      "joints": {
        "shoulder_angle": 132.74,
        "elbow_angle": 69.9,
        "hip_angle": 176.63,
        "knee_angle": 154.76,
        "ankle_angle": 120.87
      }
    },
    {
      "frame_number": 113,
      "timestamp": 1.915,
      "joints": {
        "shoulder_angle": 134.69,
        "elbow_angle": 65.22,
        "hip_angle": 175.37,
        "knee_angle": 146.16,
        "ankle_angle": 112.15
      }
    },
    {
      "frame_number": 114,
      "timestamp": 1.932,
      "joints": {
        "shoulder_angle": 138.57,
        "elbow_angle": 65.53,
        "hip_angle": 172.24,
        "knee_angle": 140.24,
        "ankle_angle": 102.13
      }
    },
    {
      "frame_number": 115,
      "timestamp": 1.949,
      "joints": {
        "shoulder_angle": 140.63,
        "elbow_angle": 72.73,
        "hip_angle": 169.28,
        "knee_angle": 129.1,
        "ankle_angle": 103.16
      }
    },
    {
      "frame_number": 116,
      "timestamp": 1.966,
      "joints": {
        "shoulder_angle": 137.39,
        "elbow_angle": 66.28,
        "hip_angle": 165.87,
        "knee_angle": 120.68,
        "ankle_angle": 103.0
      }
    },
    {
      "frame_number": 117,
      "timestamp": 1.983,
      "joints": {
        "shoulder_angle": 133.82,
        "elbow_angle": 72.44,
        "hip_angle": 160.81,
        "knee_angle": 112.28,
        "ankle_angle": 107.4
      }
    },
    {
      "frame_number": 118,
      "timestamp": 2.0,
      "joints": {
        "shoulder_angle": 132.96,
        "elbow_angle": 118.78,
        "hip_angle": 155.73,
        "knee_angle": 107.62,
        "ankle_angle": 105.28
      }
    },
    {
      "frame_number": 119,
      "timestamp": 2.017,
      "joints": {
        "shoulder_angle": 141.64,
        "elbow_angle": 128.01,
        "hip_angle": 147.91,
        "knee_angle": 103.68,
        "ankle_angle": 103.05
      }
    },
    {
      "frame_number": 120,
      "timestamp": 2.034,
      "joints": {
        "shoulder_angle": 151.69,
        "elbow_angle": 135.83,
        "hip_angle": 141.29,
        "knee_angle": 96.61,
        "ankle_angle": 110.39
      }
    },
    {
      "frame_number": 121,
      "timestamp": 2.051,
      "joints": {
        "shoulder_angle": 155.72,
        "elbow_angle": 134.96,
        "hip_angle": 136.35,
        "knee_angle": 103.43,
        "ankle_angle": 124.75
      }
    },
    {
      "frame_number": 122,
      "timestamp": 2.068,
      "joints": {
        "shoulder_angle": 150.06,
        "elbow_angle": 143.82,
        "hip_angle": 127.99,
        "knee_angle": 116.19,
        "ankle_angle": 145.56
      }
    },
    {
      "frame_number": 123,
      "timestamp": 2.085,
      "joints": {
        "shoulder_angle": 154.16,
        "elbow_angle": 142.77,
        "hip_angle": 115.2,
        "knee_angle": 108.24,
        "ankle_angle": 149.59
      }
    },
    {
      "frame_number": 124,
      "timestamp": 2.102,
      "joints": {
        "shoulder_angle": 155.63,
        "elbow_angle": 147.65,
        "hip_angle": 102.99,
        "knee_angle": 106.9,
        "ankle_angle": 130.02
      }
    },
    {
      "frame_number": 125,
      "timestamp": 2.119,
      "joints": {
        "shoulder_angle": 156.35,
        "elbow_angle": 151.05,
        "hip_angle": 91.7,
        "knee_angle": 115.28,
        "ankle_angle": 156.77
      }
    },
    {
      "frame_number": 126,
      "timestamp": 2.136,
      "joints": {
        "shoulder_angle": 150.36,
        "elbow_angle": 154.84,
        "hip_angle": 98.06,
        "knee_angle": 132.21,
        "ankle_angle": 161.37
      }
    },
    {
      "frame_number": 127,
      "timestamp": 2.153,
      "joints": {
        "shoulder_angle": 157.44,
        "elbow_angle": 158.56,
        "hip_angle": 97.72,
        "knee_angle": 141.14,
        "ankle_angle": 164.75
      }
    },
    {
      "frame_number": 128,
      "timestamp": 2.169,
      "joints": {
        "shoulder_angle": 153.95,
        "elbow_angle": 163.0,
        "hip_angle": 107.92,
        "knee_angle": 161.77,
        "ankle_angle": 157.17
      }
    },
    {
      "frame_number": 129,
      "timestamp": 2.186,
      "joints": {
        "shoulder_angle": 149.19,
        "elbow_angle": 162.3,
        "hip_angle": 105.44,
        "knee_angle": 160.5,
        "ankle_angle": 159.92
      }
    },
    {
      "frame_number": 130,
      "timestamp": 2.203,
      "joints": {
        "shoulder_angle": 151.43,
        "elbow_angle": 162.69,
        "hip_angle": 104.73,
        "knee_angle": 158.1,
        "ankle_angle": 160.99
      }
    },
    {
      "frame_number": 131,
      "timestamp": 2.22,
      "joints": {
        "shoulder_angle": 151.77,
        "elbow_angle": 164.51,
        "hip_angle": 99.02,
        "knee_angle": 148.92,
        "ankle_angle": 141.57
      }
    },
    {
      "frame_number": 132,
      "timestamp": 2.237,
      "joints": {
        "shoulder_angle": 150.51,
        "elbow_angle": 166.98,
        "hip_angle": 87.47,
        "knee_angle": 133.14,
        "ankle_angle": 150.1
      }
    },
    {
      "frame_number": 133,
      "timestamp": 2.254,
      "joints": {
        "shoulder_angle": 149.95,
        "elbow_angle": 159.52,
        "hip_angle": 79.82,
        "knee_angle": 127.8,
        "ankle_angle": 164.14
      }
    },
    {
      "frame_number": 134,
      "timestamp": 2.271,
      "joints": {
        "shoulder_angle": 153.29,
        "elbow_angle": 155.33,
        "hip_angle": 72.08,
        "knee_angle": 111.04,
        "ankle_angle": 160.1
      }
    },
    {
      "frame_number": 135,
      "timestamp": 2.288,
      "joints": {
        "shoulder_angle": 147.77,
        "elbow_angle": 155.49,
        "hip_angle": 65.71,
        "knee_angle": 96.09,
        "ankle_angle": 159.18
      }
    },
    {
      "frame_number": 136,
      "timestamp": 2.305,
      "joints": {
        "shoulder_angle": 144.91,
        "elbow_angle": 151.58,
        "hip_angle": 53.58,
        "knee_angle": 81.06,
        "ankle_angle": 154.09
      }
    },
    {
      "frame_number": 137,
      "timestamp": 2.322,
      "joints": {
        "shoulder_angle": 142.28,
        "elbow_angle": 152.72,
        "hip_angle": 46.04,
        "knee_angle": 69.51,
        "ankle_angle": 162.25
      }
    },
    {
      "frame_number": 138,
      "timestamp": 2.339,
      "joints": {
        "shoulder_angle": 138.57,
        "elbow_angle": 150.72,
        "hip_angle": 41.78,
        "knee_angle": 63.9,
        "ankle_angle": 162.93
      }
    },
    {
      "frame_number": 139,
      "timestamp": 2.356,
      "joints": {
        "shoulder_angle": 136.27,
        "elbow_angle": 147.58,
        "hip_angle": 38.97,
        "knee_angle": 57.75,
        "ankle_angle": 155.97
      }
    },
    {
      "frame_number": 140,
      "timestamp": 2.373,
      "joints": {
        "shoulder_angle": 133.68,
        "elbow_angle": 149.23,
        "hip_angle": 43.27,
        "knee_angle": 60.19,
        "ankle_angle": 141.04
      }
    },
    {
      "frame_number": 141,
      "timestamp": 2.39,
      "joints": {
        "shoulder_angle": 128.77,
        "elbow_angle": 148.05,
        "hip_angle": 47.1,
        "knee_angle": 58.56,
        "ankle_angle": 146.12
      }
    },
    {
      "frame_number": 142,
      "timestamp": 2.407,
      "joints": {
        "shoulder_angle": 125.96,
        "elbow_angle": 144.48,
        "hip_angle": 61.56,
        "knee_angle": 68.7,
        "ankle_angle": 153.89
      }
    },
    {
      "frame_number": 143,
      "timestamp": 2.424,
      "joints": {
        "shoulder_angle": 123.67,
        "elbow_angle": 138.13,
        "hip_angle": 66.04,
        "knee_angle": 69.17,
        "ankle_angle": 144.52
      }
    },
    {
      "frame_number": 144,
      "timestamp": 2.441,
      "joints": {
        "shoulder_angle": 125.41,
        "elbow_angle": 133.08,
        "hip_angle": 67.37,
        "knee_angle": 69.71,
        "ankle_angle": 129.72
      }
    },
    {
      "frame_number": 145,
      "timestamp": 2.458,
      "joints": {
        "shoulder_angle": 127.94,
        "elbow_angle": 132.33,
        "hip_angle": 62.96,
        "knee_angle": 69.61,
        "ankle_angle": 107.64
      }
    },
    {
      "frame_number": 146,
      "timestamp": 2.475,
      "joints": {
        "shoulder_angle": 127.04,
        "elbow_angle": 146.77,
        "hip_angle": 68.02,
        "knee_angle": 74.23,
        "ankle_angle": 111.63
      }
    },
    {
      "frame_number": 147,
      "timestamp": 2.492,
      "joints": {
        "shoulder_angle": 128.79,
        "elbow_angle": 152.48,
        "hip_angle": 78.86,
        "knee_angle": 82.53,
        "ankle_angle": 136.76
      }
    },
    {
      "frame_number": 148,
      "timestamp": 2.508,
      "joints": {
        "shoulder_angle": 132.15,
        "elbow_angle": 154.96,
        "hip_angle": 89.02,
        "knee_angle": 90.85,
        "ankle_angle": 147.54
      }
    },
    {
      "frame_number": 149,
      "timestamp": 2.525,
      "joints": {
        "shoulder_angle": 134.58,
        "elbow_angle": 157.25,
        "hip_angle": 97.02,
        "knee_angle": 100.05,
        "ankle_angle": 142.76
      }
    },
    {
      "frame_number": 150,
      "timestamp": 2.542,
      "joints": {
        "shoulder_angle": 136.67,
        "elbow_angle": 158.68,
        "hip_angle": 102.49,
        "knee_angle": 104.34,
        "ankle_angle": 141.82
      }
    },
    {
      "frame_number": 151,
      "timestamp": 2.559,
      "joints": {
        "shoulder_angle": 139.94,
        "elbow_angle": 157.76,
        "hip_angle": 107.95,
        "knee_angle": 111.17,
        "ankle_angle": 140.53
      }
    },
    {
      "frame_number": 152,
      "timestamp": 2.576,
      "joints": {
        "shoulder_angle": 141.46,
        "elbow_angle": 157.49,
        "hip_angle": 113.3,
        "knee_angle": 119.81,
        "ankle_angle": 137.52
      }
    },
    {
      "frame_number": 153,
      "timestamp": 2.593,
      "joints": {
        "shoulder_angle": 145.68,
        "elbow_angle": 156.67,
        "hip_angle": 115.56,
        "knee_angle": 121.08,
        "ankle_angle": 136.0
      }
    },
    {
      "frame_number": 154,
      "timestamp": 2.61,
      "joints": {
        "shoulder_angle": 147.69,
        "elbow_angle": 153.87,
        "hip_angle": 119.79,
        "knee_angle": 123.09,
        "ankle_angle": 130.87
      }
    },
    {
      "frame_number": 155,
      "timestamp": 2.627,
      "joints": {
        "shoulder_angle": 154.54,
        "elbow_angle": 157.57,
        "hip_angle": 123.64,
        "knee_angle": 125.68,
        "ankle_angle": 123.16
      }
    },
    {
      "frame_number": 156,
      "timestamp": 2.644,
      "joints": {
        "shoulder_angle": 163.61,
        "elbow_angle": 165.34,
        "hip_angle": 126.02,
        "knee_angle": 126.2,
        "ankle_angle": 107.02
      }
    },
    {
      "frame_number": 157,
      "timestamp": 2.661,
      "joints": {
        "shoulder_angle": 173.46,
        "elbow_angle": 161.61,
        "hip_angle": 127.79,
        "knee_angle": 126.42,
        "ankle_angle": 112.73
      }
    },
    {
      "frame_number": 158,
      "timestamp": 2.678,
      "joints": {
        "shoulder_angle": 177.0,
        "elbow_angle": 156.34,
        "hip_angle": 133.24,
        "knee_angle": 130.79,
        "ankle_angle": 126.19
      }
    },
    {
      "frame_number": 159,
      "timestamp": 2.695,
      "joints": {
        "shoulder_angle": 177.55,
        "elbow_angle": 158.57,
        "hip_angle": 139.76,
        "knee_angle": 138.06,
        "ankle_angle": 130.81
      }
    },
    {
      "frame_number": 160,
      "timestamp": 2.712,
      "joints": {
        "shoulder_angle": 177.45,
        "elbow_angle": 159.72,
        "hip_angle": 141.14,
        "knee_angle": 137.27,
        "ankle_angle": 134.3
      }
    },
    {
      "frame_number": 161,
      "timestamp": 2.729,
      "joints": {
        "shoulder_angle": 178.45,
        "elbow_angle": 160.5,
        "hip_angle": 143.08,
        "knee_angle": 139.85,
        "ankle_angle": 137.96
      }
    },
    {
      "frame_number": 162,
      "timestamp": 2.746,
      "joints": {
        "shoulder_angle": 177.46,
        "elbow_angle": 161.93,
        "hip_angle": 145.48,
        "knee_angle": 141.9,
        "ankle_angle": 145.07
      }
    },
    {
      "frame_number": 163,
      "timestamp": 2.763,
      "joints": {
        "shoulder_angle": 175.06,
        "elbow_angle": 162.95,
        "hip_angle": 146.18,
        "knee_angle": 143.8,
        "ankle_angle": 150.34
      }
    },
    {
      "frame_number": 164,
      "timestamp": 2.78,
      "joints": {
        "shoulder_angle": 176.89,
        "elbow_angle": 162.92,
        "hip_angle": 146.3,
        "knee_angle": 144.85,
        "ankle_angle": 153.08
      }
    },
    {
      "frame_number": 165,
      "timestamp": 2.797,
      "joints": {
        "shoulder_angle": 177.74,
        "elbow_angle": 166.56,
        "hip_angle": 148.17,
        "knee_angle": 146.92,
        "ankle_angle": 155.98
      }
    },
    {
      "frame_number": 166,
      "timestamp": 2.814,
      "joints": {
        "shoulder_angle": 178.09,
        "elbow_angle": 164.91,
        "hip_angle": 150.86,
        "knee_angle": 151.2,
        "ankle_angle": 160.15
      }
    }
  ]
}